README.md
setup.py
cristin/__init__.py
cristin/_version.py
cristin.egg-info/PKG-INFO
cristin.egg-info/SOURCES.txt
cristin.egg-info/dependency_links.txt
cristin.egg-info/entry_points.txt
cristin.egg-info/requires.txt
cristin.egg-info/top_level.txt