Metadata-Version: 2.1
Name: cristin
Version: 0.0.1
Summary: cristin API
Home-page: https://github.com/pgdr/cristin
Author: PG Drange
Author-email: Pal.Drange@uib.no
Maintainer: PG Drange <Pal.Drange@uib.no>
License: MIT
Project-URL: Bug Tracker, https://github.com/pgdr/cristin/issues
Project-URL: Documentation, https://github.com/pgdr/cristin/blob/master/README.md
Project-URL: Source Code, https://github.com/pgdr/cristin
Keywords: cristin
